[{"kata":"ada"},{"kata":"adalah"},{"kata":"adanya"},{"kata":"adapun"},{"kata":"agak"},{"kata":"agaknya"},{"kata":"agar"},{"kata":"akan"},{"kata":"akankah"},{"kata":"akhir"},{"kata":"akhiri"},{"kata":"akhirnya"},{"kata":"aku"},{"kata":"akulah"},{"kata":"amat"},{"kata":"amatlah"},{"kata":"anda"},{"kata":"andalah"},{"kata":"antar"},{"kata":"antara"},{"kata":"antaranya"},{"kata":"apa"},{"kata":"apaan"},{"kata":"apabila"},{"kata":"apakah"},{"kata":"apalagi"},{"kata":"apatah"},{"kata":"artinya"},{"kata":"asal"},{"kata":"asalkan"},{"kata":"atas"},{"kata":"atau"},{"kata":"ataukah"},{"kata":"ataupun"},{"kata":"awal"},{"kata":"awalnya"},{"kata":"bagai"},{"kata":"bagaikan"},{"kata":"bagaimana"},{"kata":"bagaimanakah"},{"kata":"bagaimanapun"},{"kata":"bagi"},{"kata":"bagian"},{"kata":"bahkan"},{"kata":"bahwa"},{"kata":"bahwasanya"},{"kata":"baik"},{"kata":"bakal"},{"kata":"bakalan"},{"kata":"balik"},{"kata":"banyak"},{"kata":"bapak"},{"kata":"baru"},{"kata":"bawah"},{"kata":"beberapa"},{"kata":"begini"},{"kata":"beginian"},{"kata":"beginikah"},{"kata":"beginilah"},{"kata":"begitu"},{"kata":"begitukah"},{"kata":"begitulah"},{"kata":"begitupun"},{"kata":"bekerja"},{"kata":"belakang"},{"kata":"belakangan"},{"kata":"belum"},{"kata":"belumlah"},{"kata":"benar"},{"kata":"benarkah"},{"kata":"benarlah"},{"kata":"berada"},{"kata":"berakhir"},{"kata":"berakhirlah"},{"kata":"berakhirnya"},{"kata":"berapa"},{"kata":"berapakah"},{"kata":"berapalah"},{"kata":"berapapun"},{"kata":"berarti"},{"kata":"berawal"},{"kata":"berbagai"},{"kata":"berdatangan"},{"kata":"beri"},{"kata":"berikan"},{"kata":"berikut"},{"kata":"berikutnya"},{"kata":"berjumlah"},{"kata":"berkali-kali"},{"kata":"berkata"},{"kata":"berkehendak"},{"kata":"berkeinginan"},{"kata":"berkenaan"},{"kata":"berlainan"},{"kata":"berlalu"},{"kata":"berlangsung"},{"kata":"berlebihan"},{"kata":"bermacam"},{"kata":"bermacam-macam"},{"kata":"bermaksud"},{"kata":"bermula"},{"kata":"bersama"},{"kata":"bersama-sama"},{"kata":"bersiap"},{"kata":"bersiap-siap"},{"kata":"bertanya"},{"kata":"bertanya-tanya"},{"kata":"berturut"},{"kata":"berturut-turut"},{"kata":"bertutur"},{"kata":"berujar"},{"kata":"berupa"},{"kata":"besar"},{"kata":"betul"},{"kata":"betulkah"},{"kata":"biasa"},{"kata":"biasanya"},{"kata":"bila"},{"kata":"bilakah"},{"kata":"bisa"},{"kata":"bisakah"},{"kata":"boleh"},{"kata":"bolehkah"},{"kata":"bolehlah"},{"kata":"buat"},{"kata":"bukan"},{"kata":"bukankah"},{"kata":"bukanlah"},{"kata":"bukannya"},{"kata":"bulan"},{"kata":"bung"},{"kata":"cara"},{"kata":"caranya"},{"kata":"cukup"},{"kata":"cukupkah"},{"kata":"cukuplah"},{"kata":"cuma"},{"kata":"dahulu"},{"kata":"dalam"},{"kata":"dan"},{"kata":"dapat"},{"kata":"dari"},{"kata":"daripada"},{"kata":"datang"},{"kata":"dekat"},{"kata":"demi"},{"kata":"demikian"},{"kata":"demikianlah"},{"kata":"dengan"},{"kata":"depan"},{"kata":"di"},{"kata":"dia"},{"kata":"diakhiri"},{"kata":"diakhirinya"},{"kata":"dialah"},{"kata":"diantara"},{"kata":"diantaranya"},{"kata":"diberi"},{"kata":"diberikan"},{"kata":"diberikannya"},{"kata":"dibuat"},{"kata":"dibuatnya"},{"kata":"didapat"},{"kata":"didatangkan"},{"kata":"digunakan"},{"kata":"diibaratkan"},{"kata":"diibaratkannya"},{"kata":"diingat"},{"kata":"diingatkan"},{"kata":"diinginkan"},{"kata":"dijawab"},{"kata":"dijelaskan"},{"kata":"dijelaskannya"},{"kata":"dikarenakan"},{"kata":"dikatakan"},{"kata":"dikatakannya"},{"kata":"dikerjakan"},{"kata":"diketahui"},{"kata":"diketahuinya"},{"kata":"dikira"},{"kata":"dilakukan"},{"kata":"dilalui"},{"kata":"dilihat"},{"kata":"dimaksud"},{"kata":"dimaksudkan"},{"kata":"dimaksudkannya"},{"kata":"dimaksudnya"},{"kata":"diminta"},{"kata":"dimintai"},{"kata":"dimisalkan"},{"kata":"dimulai"},{"kata":"dimulailah"},{"kata":"dimulainya"},{"kata":"dimungkinkan"},{"kata":"dini"},{"kata":"dipastikan"},{"kata":"diperbuat"},{"kata":"diperbuatnya"},{"kata":"dipergunakan"},{"kata":"diperkirakan"},{"kata":"diperlihatkan"},{"kata":"diperlukan"},{"kata":"diperlukannya"},{"kata":"dipersoalkan"},{"kata":"dipertanyakan"},{"kata":"dipunyai"},{"kata":"diri"},{"kata":"dirinya"},{"kata":"disampaikan"},{"kata":"disebut"},{"kata":"disebutkan"},{"kata":"disebutkannya"},{"kata":"disini"},{"kata":"disinilah"},{"kata":"ditambahkan"},{"kata":"ditandaskan"},{"kata":"ditanya"},{"kata":"ditanyai"},{"kata":"ditanyakan"},{"kata":"ditegaskan"},{"kata":"ditujukan"},{"kata":"ditunjuk"},{"kata":"ditunjuki"},{"kata":"ditunjukkan"},{"kata":"ditunjukkannya"},{"kata":"ditunjuknya"},{"kata":"dituturkan"},{"kata":"dituturkannya"},{"kata":"diucapkan"},{"kata":"diucapkannya"},{"kata":"diungkapkan"},{"kata":"dong"},{"kata":"dua"},{"kata":"dulu"},{"kata":"empat"},{"kata":"enggak"},{"kata":"enggaknya"},{"kata":"entah"},{"kata":"entahlah"},{"kata":"guna"},{"kata":"gunakan"},{"kata":"hal"},{"kata":"hampir"},{"kata":"hanya"},{"kata":"hanyalah"},{"kata":"hari"},{"kata":"harus"},{"kata":"haruslah"},{"kata":"harusnya"},{"kata":"hendak"},{"kata":"hendaklah"},{"kata":"hendaknya"},{"kata":"hingga"},{"kata":"ia"},{"kata":"ialah"},{"kata":"ibarat"},{"kata":"ibaratkan"},{"kata":"ibaratnya"},{"kata":"ibu"},{"kata":"ikut"},{"kata":"ingat"},{"kata":"ingat-ingat"},{"kata":"ingin"},{"kata":"inginkah"},{"kata":"inginkan"},{"kata":"ini"},{"kata":"inikah"},{"kata":"inilah"},{"kata":"itu"},{"kata":"itukah"},{"kata":"itulah"},{"kata":"jadi"},{"kata":"jadilah"},{"kata":"jadinya"},{"kata":"jangan"},{"kata":"jangankan"},{"kata":"janganlah"},{"kata":"jauh"},{"kata":"jawab"},{"kata":"jawaban"},{"kata":"jawabnya"},{"kata":"jelas"},{"kata":"jelaskan"},{"kata":"jelaslah"},{"kata":"jelasnya"},{"kata":"jika"},{"kata":"jikalau"},{"kata":"juga"},{"kata":"jumlah"},{"kata":"jumlahnya"},{"kata":"justru"},{"kata":"kala"},{"kata":"kalau"},{"kata":"kalaulah"},{"kata":"kalaupun"},{"kata":"kalian"},{"kata":"kami"},{"kata":"kamilah"},{"kata":"kamu"},{"kata":"kamulah"},{"kata":"kan"},{"kata":"kapan"},{"kata":"kapankah"},{"kata":"kapanpun"},{"kata":"karena"},{"kata":"karenanya"},{"kata":"kasus"},{"kata":"kata"},{"kata":"katakan"},{"kata":"katakanlah"},{"kata":"katanya"},{"kata":"ke"},{"kata":"keadaan"},{"kata":"kebetulan"},{"kata":"kecil"},{"kata":"kedua"},{"kata":"keduanya"},{"kata":"keinginan"},{"kata":"kelamaan"},{"kata":"kelihatan"},{"kata":"kelihatannya"},{"kata":"kelima"},{"kata":"keluar"},{"kata":"kembali"},{"kata":"kemudian"},{"kata":"kemungkinan"},{"kata":"kemungkinannya"},{"kata":"kenapa"},{"kata":"kepada"},{"kata":"kepadanya"},{"kata":"kesampaian"},{"kata":"keseluruhan"},{"kata":"keseluruhannya"},{"kata":"keterlaluan"},{"kata":"ketika"},{"kata":"khususnya"},{"kata":"kini"},{"kata":"kinilah"},{"kata":"kira"},{"kata":"kira-kira"},{"kata":"kiranya"},{"kata":"kita"},{"kata":"kitalah"},{"kata":"kok"},{"kata":"kurang"},{"kata":"lagi"},{"kata":"lagian"},{"kata":"lah"},{"kata":"lain"},{"kata":"lainnya"},{"kata":"lalu"},{"kata":"lama"},{"kata":"lamanya"},{"kata":"lanjut"},{"kata":"lanjutnya"},{"kata":"lebih"},{"kata":"lewat"},{"kata":"lima"},{"kata":"luar"},{"kata":"macam"},{"kata":"maka"},{"kata":"makanya"},{"kata":"makin"},{"kata":"malah"},{"kata":"malahan"},{"kata":"mampu"},{"kata":"mampukah"},{"kata":"mana"},{"kata":"manakala"},{"kata":"manalagi"},{"kata":"masa"},{"kata":"masalah"},{"kata":"masalahnya"},{"kata":"masih"},{"kata":"masihkah"},{"kata":"masing"},{"kata":"masing-masing"},{"kata":"mau"},{"kata":"maupun"},{"kata":"melainkan"},{"kata":"melakukan"},{"kata":"melalui"},{"kata":"melihat"},{"kata":"melihatnya"},{"kata":"memang"},{"kata":"memastikan"},{"kata":"memberi"},{"kata":"memberikan"},{"kata":"membuat"},{"kata":"memerlukan"},{"kata":"memihak"},{"kata":"meminta"},{"kata":"memintakan"},{"kata":"memisalkan"},{"kata":"memperbuat"},{"kata":"mempergunakan"},{"kata":"memperkirakan"},{"kata":"memperlihatkan"},{"kata":"mempersiapkan"},{"kata":"mempersoalkan"},{"kata":"mempertanyakan"},{"kata":"mempunyai"},{"kata":"memulai"},{"kata":"memungkinkan"},{"kata":"menaiki"},{"kata":"menambahkan"},{"kata":"menandaskan"},{"kata":"menanti"},{"kata":"menanti-nanti"},{"kata":"menantikan"},{"kata":"menanya"},{"kata":"menanyai"},{"kata":"menanyakan"},{"kata":"mendapat"},{"kata":"mendapatkan"},{"kata":"mendatang"},{"kata":"mendatangi"},{"kata":"mendatangkan"},{"kata":"menegaskan"},{"kata":"mengakhiri"},{"kata":"mengapa"},{"kata":"mengatakan"},{"kata":"mengatakannya"},{"kata":"mengenai"},{"kata":"mengerjakan"},{"kata":"mengetahui"},{"kata":"menggunakan"},{"kata":"menghendaki"},{"kata":"mengibaratkan"},{"kata":"mengibaratkannya"},{"kata":"mengingat"},{"kata":"mengingatkan"},{"kata":"menginginkan"},{"kata":"mengira"},{"kata":"mengucapkan"},{"kata":"mengucapkannya"},{"kata":"mengungkapkan"},{"kata":"menjadi"},{"kata":"menjawab"},{"kata":"menjelaskan"},{"kata":"menuju"},{"kata":"menunjuk"},{"kata":"menunjuki"},{"kata":"menunjukkan"},{"kata":"menunjuknya"},{"kata":"menurut"},{"kata":"menuturkan"},{"kata":"menyampaikan"},{"kata":"menyangkut"},{"kata":"menyatakan"},{"kata":"menyebutkan"},{"kata":"menyeluruh"},{"kata":"menyiapkan"},{"kata":"merasa"},{"kata":"mereka"},{"kata":"merekalah"},{"kata":"merupakan"},{"kata":"meski"},{"kata":"meskipun"},{"kata":"meyakini"},{"kata":"meyakinkan"},{"kata":"minta"},{"kata":"mirip"},{"kata":"misal"},{"kata":"misalkan"},{"kata":"misalnya"},{"kata":"mula"},{"kata":"mulai"},{"kata":"mulailah"},{"kata":"mulanya"},{"kata":"mungkin"},{"kata":"mungkinkah"},{"kata":"nah"},{"kata":"naik"},{"kata":"namun"},{"kata":"nanti"},{"kata":"nantinya"},{"kata":"nyaris"},{"kata":"nyatanya"},{"kata":"oleh"},{"kata":"olehnya"},{"kata":"pada"},{"kata":"padahal"},{"kata":"padanya"},{"kata":"pak"},{"kata":"paling"},{"kata":"panjang"},{"kata":"pantas"},{"kata":"para"},{"kata":"pasti"},{"kata":"pastilah"},{"kata":"penting"},{"kata":"pentingnya"},{"kata":"per"},{"kata":"percuma"},{"kata":"perlu"},{"kata":"perlukah"},{"kata":"perlunya"},{"kata":"pernah"},{"kata":"persoalan"},{"kata":"pertama"},{"kata":"pertama-tama"},{"kata":"pertanyaan"},{"kata":"pertanyakan"},{"kata":"pihak"},{"kata":"pihaknya"},{"kata":"pukul"},{"kata":"pula"},{"kata":"pun"},{"kata":"punya"},{"kata":"rasa"},{"kata":"rasanya"},{"kata":"rata"},{"kata":"rupanya"},{"kata":"saat"},{"kata":"saatnya"},{"kata":"saja"},{"kata":"sajalah"},{"kata":"saling"},{"kata":"sama"},{"kata":"sama-sama"},{"kata":"sambil"},{"kata":"sampai"},{"kata":"sampai-sampai"},{"kata":"sampaikan"},{"kata":"sana"},{"kata":"sangat"},{"kata":"sangatlah"},{"kata":"satu"},{"kata":"saya"},{"kata":"sayalah"},{"kata":"se"},{"kata":"sebab"},{"kata":"sebabnya"},{"kata":"sebagai"},{"kata":"sebagaimana"},{"kata":"sebagainya"},{"kata":"sebagian"},{"kata":"sebaik"},{"kata":"sebaik-baiknya"},{"kata":"sebaiknya"},{"kata":"sebaliknya"},{"kata":"sebanyak"},{"kata":"sebegini"},{"kata":"sebegitu"},{"kata":"sebelum"},{"kata":"sebelumnya"},{"kata":"sebenarnya"},{"kata":"seberapa"},{"kata":"sebesar"},{"kata":"sebetulnya"},{"kata":"sebisanya"},{"kata":"sebuah"},{"kata":"sebut"},{"kata":"sebutlah"},{"kata":"sebutnya"},{"kata":"secara"},{"kata":"secukupnya"},{"kata":"sedang"},{"kata":"sedangkan"},{"kata":"sedemikian"},{"kata":"sedikit"},{"kata":"sedikitnya"},{"kata":"seenaknya"},{"kata":"segala"},{"kata":"segalanya"},{"kata":"segera"},{"kata":"seharusnya"},{"kata":"sehingga"},{"kata":"seingat"},{"kata":"sejak"},{"kata":"sejauh"},{"kata":"sejenak"},{"kata":"sejumlah"},{"kata":"sekadar"},{"kata":"sekadarnya"},{"kata":"sekali"},{"kata":"sekali-kali"},{"kata":"sekalian"},{"kata":"sekaligus"},{"kata":"sekalipun"},{"kata":"sekarang"},{"kata":"sekecil"},{"kata":"seketika"},{"kata":"sekiranya"},{"kata":"sekitar"},{"kata":"sekitarnya"},{"kata":"sekurang-kurangnya"},{"kata":"sekurangnya"},{"kata":"sela"},{"kata":"selain"},{"kata":"selaku"},{"kata":"selalu"},{"kata":"selama"},{"kata":"selama-lamanya"},{"kata":"selamanya"},{"kata":"selanjutnya"},{"kata":"seluruh"},{"kata":"seluruhnya"},{"kata":"semacam"},{"kata":"semakin"},{"kata":"semampu"},{"kata":"semampunya"},{"kata":"semasa"},{"kata":"semasih"},{"kata":"semata"},{"kata":"semata-mata"},{"kata":"semaunya"},{"kata":"sementara"},{"kata":"semisal"},{"kata":"semisalnya"},{"kata":"sempat"},{"kata":"semua"},{"kata":"semuanya"},{"kata":"semula"},{"kata":"sendiri"},{"kata":"sendirian"},{"kata":"sendirinya"},{"kata":"seolah"},{"kata":"seolah-olah"},{"kata":"seorang"},{"kata":"sepanjang"},{"kata":"sepantasnya"},{"kata":"sepantasnyalah"},{"kata":"seperlunya"},{"kata":"seperti"},{"kata":"sepertinya"},{"kata":"sepihak"},{"kata":"sering"},{"kata":"seringnya"},{"kata":"serta"},{"kata":"serupa"},{"kata":"sesaat"},{"kata":"sesama"},{"kata":"sesampai"},{"kata":"sesegera"},{"kata":"sesekali"},{"kata":"seseorang"},{"kata":"sesuatu"},{"kata":"sesuatunya"},{"kata":"sesudah"},{"kata":"sesudahnya"},{"kata":"setelah"},{"kata":"setempat"},{"kata":"setengah"},{"kata":"seterusnya"},{"kata":"setiap"},{"kata":"setiba"},{"kata":"setibanya"},{"kata":"setidak-tidaknya"},{"kata":"setidaknya"},{"kata":"setinggi"},{"kata":"seusai"},{"kata":"sewaktu"},{"kata":"siap"},{"kata":"siapa"},{"kata":"siapakah"},{"kata":"siapapun"},{"kata":"sini"},{"kata":"sinilah"},{"kata":"soal"},{"kata":"soalnya"},{"kata":"suatu"},{"kata":"sudah"},{"kata":"sudahkah"},{"kata":"sudahlah"},{"kata":"supaya"},{"kata":"tadi"},{"kata":"tadinya"},{"kata":"tahu"},{"kata":"tahun"},{"kata":"tak"},{"kata":"tambah"},{"kata":"tambahnya"},{"kata":"tampak"},{"kata":"tampaknya"},{"kata":"tandas"},{"kata":"tandasnya"},{"kata":"tanpa"},{"kata":"tanya"},{"kata":"tanyakan"},{"kata":"tanyanya"},{"kata":"tapi"},{"kata":"tegas"},{"kata":"tegasnya"},{"kata":"telah"},{"kata":"tempat"},{"kata":"tengah"},{"kata":"tentang"},{"kata":"tentu"},{"kata":"tentulah"},{"kata":"tentunya"},{"kata":"tepat"},{"kata":"terakhir"},{"kata":"terasa"},{"kata":"terbanyak"},{"kata":"terdahulu"},{"kata":"terdapat"},{"kata":"terdiri"},{"kata":"terhadap"},{"kata":"terhadapnya"},{"kata":"teringat"},{"kata":"teringat-ingat"},{"kata":"terjadi"},{"kata":"terjadilah"},{"kata":"terjadinya"},{"kata":"terkira"},{"kata":"terlalu"},{"kata":"terlebih"},{"kata":"terlihat"},{"kata":"termasuk"},{"kata":"ternyata"},{"kata":"tersampaikan"},{"kata":"tersebut"},{"kata":"tersebutlah"},{"kata":"tertentu"},{"kata":"tertuju"},{"kata":"terus"},{"kata":"terutama"},{"kata":"tetap"},{"kata":"tetapi"},{"kata":"tiap"},{"kata":"tiba"},{"kata":"tiba-tiba"},{"kata":"tidak"},{"kata":"tidakkah"},{"kata":"tidaklah"},{"kata":"tiga"},{"kata":"tinggi"},{"kata":"toh"},{"kata":"tunjuk"},{"kata":"turut"},{"kata":"tutur"},{"kata":"tuturnya"},{"kata":"ucap"},{"kata":"ucapnya"},{"kata":"ujar"},{"kata":"ujarnya"},{"kata":"umum"},{"kata":"umumnya"},{"kata":"ungkap"},{"kata":"ungkapnya"},{"kata":"untuk"},{"kata":"usah"},{"kata":"usai"},{"kata":"waduh"},{"kata":"wah"},{"kata":"wahai"},{"kata":"waktu"},{"kata":"waktunya"},{"kata":"walau"},{"kata":"walaupun"},{"kata":"wong"},{"kata":"yaitu"},{"kata":"yakin"},{"kata":"yakni"},{"kata":"yang"},{"kata":"a"},{"kata":"aa"},{"kata":"b"},{"kata":"c"},{"kata":"d"},{"kata":"e"},{"kata":"f"},{"kata":"g"},{"kata":"h"},{"kata":"i"},{"kata":"j"},{"kata":"k"},{"kata":"l"},{"kata":"m"},{"kata":"n"},{"kata":"o"},{"kata":"p"},{"kata":"q"},{"kata":"r"},{"kata":"s"},{"kata":"t"},{"kata":"u"},{"kata":"v"},{"kata":"w"},{"kata":"x"},{"kata":"y"},{"kata":"z"},{"kata":"for"},{"kata":"am"},{"kata":"is"},{"kata":"are"},{"kata":"to"},{"kata":"and"},{"kata":"or"}]